filter_certwarning/__init__.py
filter_certwarning/filters.py
filter_certwarning-1.0.1.dist-info/LICENSE
filter_certwarning-1.0.1.dist-info/METADATA
filter_certwarning-1.0.1.dist-info/WHEEL
filter_certwarning-1.0.1.dist-info/top_level.txt
filter_certwarning-1.0.1.dist-info/RECORD
