Metadata-Version: 2.1
Name: filter-certwarning
Version: 1.0.1
Summary: Decorators for filtering InsecureRequestWarnings in requests and urllib3 apps
Author-email: Darren P Meyer <darren+filtercertwarning@darrenpmeyer.com>
License: BSD-2-Clause
Project-URL: Repository, https://github.com/darrenpmeyer/filter-certwarning.git
Project-URL: Homepage, https://github.com/darrenpmeyer/filter-certwarning
Keywords: certwarning,urllib3,certificate,warnings
Classifier: Development Status :: 5 - Production/Stable
Classifier: Operating System :: POSIX
Classifier: License :: OSI Approved :: BSD License
Classifier: Programming Language :: Python :: 3 :: Only
Requires-Python: >=3.5
License-File: LICENSE
Requires-Dist: urllib3
